CHANGES
CONTRIBUTORS.txt
LICENSE
README.txt
setup.py
afpy/__init__.py
afpy.xap.egg-info/PKG-INFO
afpy.xap.egg-info/SOURCES.txt
afpy.xap.egg-info/dependency_links.txt
afpy.xap.egg-info/entry_points.txt
afpy.xap.egg-info/namespace_packages.txt
afpy.xap.egg-info/not-zip-safe
afpy.xap.egg-info/requires.txt
afpy.xap.egg-info/top_level.txt
afpy/xap/COPYING.txt
afpy/xap/HISTORY.txt
afpy/xap/README.txt
afpy/xap/VERSION.txt
afpy/xap/__init__.py
afpy/xap/indexer.py
afpy/xap/model.py
afpy/xap/run.py
afpy/xap/searcher.py
afpy/xap/settings.py
afpy/xap/xapindexer.py
afpy/xap/docs/indexer.txt
afpy/xap/tests/test_docs.py
afpy/xap/tokenizer/__init__.py
afpy/xap/tokenizer/filters.py
afpy/xap/tokenizer/normalized.fr.txt
afpy/xap/tokenizer/normalized.txt
afpy/xap/tokenizer/stopwords.fr.txt
afpy/xap/tokenizer/stopwords.txt
afpy/xap/tokenizer/tests.py
afpy/xap/tokenizer/tokenizer.txt