Metadata-Version: 1.0
Name: afpy.xap
Version: 0.1
Summary: afpy xapian indexer package
Home-page: http://afpy.org
Author: Tarek Ziade
Author-email: tarek@ziade.org
License: Python
Keywords: afpy xapian
Platform: UNKNOWN
Classifier: Programming Language :: Python
Classifier: Topic :: Software Development :: Libraries :: Python Modules
Classifier: License :: OSI Approved :: Python Software Foundation License
